{
    "AX": {
        "error": 0.010192254388596384,
        "error_type": "SEM",
        "filter_outliers_dict": {
            "filter_outliers": true,
            "iterations": 1,
            "std_devs": 3,
            "use_iqr_filtering": false,
            "use_standard_deviation_filtering": false
        },
        "fit": "average",
        "fn": 25,
        "include_baseline_error": false,
        "n": 25,
        "outlier_excluded": [],
        "reviewed": true,
        "user_excluded": [],
        "value": -0.026699106898158787
    },
    "CDD": {
        "error": 6.076574209146202e-06,
        "error_type": "SEM",
        "filter_outliers_dict": {
            "filter_outliers": true,
            "iterations": 1,
            "std_devs": 10,
            "use_iqr_filtering": false,
            "use_standard_deviation_filtering": false
        },
        "fit": "average",
        "fn": 25,
        "include_baseline_error": false,
        "n": 25,
        "outlier_excluded": [],
        "reviewed": true,
        "user_excluded": [],
        "value": 6.076574209146202e-06
    },
    "H1": {
        "error": 0.009373156657929142,
        "error_type": "SEM",
        "filter_outliers_dict": {
            "filter_outliers": true,
            "iterations": 1,
            "std_devs": 3,
            "use_iqr_filtering": false,
            "use_standard_deviation_filtering": false
        },
        "fit": "average",
        "fn": 25,
        "include_baseline_error": false,
        "n": 25,
        "outlier_excluded": [],
        "reviewed": true,
        "user_excluded": [],
        "value": 0.009080025693401694
    },
    "H2": {
        "error": 0.025014249621335485,
        "error_type": "SEM",
        "filter_outliers_dict": {
            "filter_outliers": true,
            "iterations": 1,
            "std_devs": 3,
            "use_iqr_filtering": false,
            "use_standard_deviation_filtering": false
        },
        "fit": "average",
        "fn": 25,
        "include_baseline_error": false,
        "n": 25,
        "outlier_excluded": [],
        "reviewed": true,
        "user_excluded": [],
        "value": 0.019676565598929302
    },
    "L1": {
        "error": 0.004257688480026216,
        "error_type": "SEM",
        "filter_outliers_dict": {
            "filter_outliers": true,
            "iterations": 1,
            "std_devs": 3,
            "use_iqr_filtering": false,
            "use_standard_deviation_filtering": false
        },
        "fit": "average",
        "fn": 25,
        "include_baseline_error": false,
        "n": 25,
        "outlier_excluded": [],
        "reviewed": true,
        "user_excluded": [],
        "value": -0.054810518734157085
    },
    "L2": {
        "error": 0.008300171979674063,
        "error_type": "SEM",
        "filter_outliers_dict": {
            "filter_outliers": true,
            "iterations": 1,
            "std_devs": 2
        },
        "fit": "Average",
        "fn": 25,
        "include_baseline_error": false,
        "n": 25,
        "reviewed": true,
        "value": -0.05597825476940235
    }
}